wassersteinwormhole/DefaultConfig.py
wassersteinwormhole/SpatialWormhole.py
wassersteinwormhole/Wormhole.py
wassersteinwormhole/__init__.py
wassersteinwormhole/_utils_Processing.py
wassersteinwormhole/_utils_Transformer.py
wassersteinwormhole/_utils_WeightedAttention.py
wassersteinwormhole/utils_OT.py
wassersteinwormhole-0.3.6.dist-info/LICENSE
wassersteinwormhole-0.3.6.dist-info/METADATA
wassersteinwormhole-0.3.6.dist-info/WHEEL
wassersteinwormhole-0.3.6.dist-info/RECORD
