Metadata-Version: 2.1
Name: wassersteinwormhole
Version: 0.3.6
Summary: Transformer based embeddings for Wasserstein Distances
License: MIT
Author: Doron Haviv
Requires-Python: >=3.9,<4.0
Classifier: License :: OSI Approved :: MIT License
Classifier: Programming Language :: Python :: 3
Classifier: Programming Language :: Python :: 3.9
Classifier: Programming Language :: Python :: 3.10
Classifier: Programming Language :: Python :: 3.11
Requires-Dist: clu (>=0.0.12,<0.0.13)
Requires-Dist: flax (>=0.10.6,<0.11.0)
Requires-Dist: ott-jax (>=0.4.9,<0.5.0)
Requires-Dist: scanpy (>=1.11.2,<2.0.0)
Requires-Dist: tqdm (>=4.67.1,<5.0.0)
